ripix/__init__.py
ripix/pixel.py
ripix/py.typed
ripix-2.5.0.dist-info/METADATA
ripix-2.5.0.dist-info/WHEEL
ripix-2.5.0.dist-info/RECORD
