Metadata-Version: 2.1
Name: ripix
Version: 2.5.0
Summary: A Rich-compatible library for writing pixel images and ASCII art to the terminal.
Home-page: https://github.com/romanin-rf/ripix
Keywords: ripix,rich,textual,image,pixels,ascii-art,rich_pixels
Author: Darren Burns
Author-email: darrenb900@gmail.com
Requires-Python: >=3.7,<3.12
Classifier: Programming Language :: Python :: 3
Classifier: Programming Language :: Python :: 3.7
Classifier: Programming Language :: Python :: 3.8
Classifier: Programming Language :: Python :: 3.9
Classifier: Programming Language :: Python :: 3.10
Classifier: Programming Language :: Python :: 3.11
Requires-Dist: asyncio (>=3.4)
Requires-Dist: pillow (>=9.5)
Requires-Dist: rich (>=13.5)
Project-URL: Repository, https://github.com/romanin-rf/ripix
